Metadata-Version: 2.4
Name: zipline-ai
Version: 2025.12.22
Summary: CLI tool for the Zipline AI platform
Author-email: Zipline AI <hello@zipline.ai>
License: Apache License 2.0
Project-URL: homepage, https://zipline.ai
Project-URL: documentation, https://docs.zipline.ai
Project-URL: github, https://github.com/zipline-ai/chronon/
Requires-Python: >=3.11
Requires-Dist: azure-core==1.38.0
Requires-Dist: azure-identity==1.25.1
Requires-Dist: boto3==1.42.34
Requires-Dist: botocore==1.42.34
Requires-Dist: certifi==2026.1.4
Requires-Dist: cffi==2.0.0
Requires-Dist: charset-normalizer==3.4.4
Requires-Dist: click==8.3.1
Requires-Dist: crcmod==1.7
Requires-Dist: croniter==6.0.0
Requires-Dist: cryptography==46.0.3
Requires-Dist: gitdb==4.0.12
Requires-Dist: gitpython==3.1.46
Requires-Dist: google-api-core[grpc]==2.27.0
Requires-Dist: google-auth==2.48.0
Requires-Dist: google-cloud-bigquery-storage==2.36.0
Requires-Dist: google-cloud-core==2.5.0
Requires-Dist: google-cloud-iam==2.21.0
Requires-Dist: google-cloud-storage==2.19.0
Requires-Dist: google-crc32c==1.8.0
Requires-Dist: google-resumable-media==2.8.0
Requires-Dist: googleapis-common-protos[grpc]==1.72.0
Requires-Dist: grpc-google-iam-v1==0.14.3
Requires-Dist: grpcio==1.76.0
Requires-Dist: grpcio-status==1.76.0
Requires-Dist: idna==3.11
Requires-Dist: importlib-resources==6.5.2
Requires-Dist: jmespath==1.1.0
Requires-Dist: markdown-it-py==4.0.0
Requires-Dist: mdurl==0.1.2
Requires-Dist: msal==1.34.0
Requires-Dist: msal-extensions==1.3.1
Requires-Dist: proto-plus==1.27.0
Requires-Dist: protobuf==6.33.4
Requires-Dist: py4j==0.10.9.7
Requires-Dist: pyasn1==0.6.2
Requires-Dist: pyasn1-modules==0.4.2
Requires-Dist: pycparser==3.0
Requires-Dist: pygments==2.19.2
Requires-Dist: pyjwt[crypto]==2.10.1
Requires-Dist: pyspark==3.5.4
Requires-Dist: python-dateutil==2.9.0.post0
Requires-Dist: pytz==2025.2
Requires-Dist: requests==2.32.5
Requires-Dist: rich==14.3.1
Requires-Dist: rsa==4.9.1
Requires-Dist: s3transfer==0.16.0
Requires-Dist: six==1.17.0
Requires-Dist: smmap==5.0.2
Requires-Dist: sqlglot==28.6.0
Requires-Dist: thrift==0.21.0
Requires-Dist: typing-extensions==4.15.0
Requires-Dist: urllib3==2.6.3
